{
  "version": "6",
  "dialect": "sqlite",
  "id": "24e00b1c-3210-4fab-84fd-1af713890310",
  "prevId": "c9f96034-2e05-462e-987e-549f44042842",
  "tables": {
    "brands": {
      "name": "brands",
      "columns": {
        "id": {
          "name": "id",
          "type": "integer",
          "primaryKey": true,
          "notNull": true,
          "autoincrement": true
        },
        "name": {
          "name": "name",
          "type": "text",
          "primaryKey": false,
          "notNull": true,
          "autoincrement": false
        },
        "country": {
          "name": "country",
          "type": "text",
          "primaryKey": false,
          "notNull": true,
          "autoincrement": false
        },
        "description": {
          "name": "description",
          "type": "text",
          "primaryKey": false,
          "notNull": false,
          "autoincrement": false
        },
        "created_at": {
          "name": "created_at",
          "type": "integer",
          "primaryKey": false,
          "notNull": false,
          "autoincrement": false,
          "default": "'\"2025-09-03T16:07:20.494Z\"'"
        }
      },
      "indexes": {
        "Brand name must be unique": {
          "name": "Brand name must be unique",
          "columns": [
            "name"
          ],
          "isUnique": true
        }
      },
      "foreignKeys": {},
      "compositePrimaryKeys": {},
      "uniqueConstraints": {},
      "checkConstraints": {}
    },
    "categories": {
      "name": "categories",
      "columns": {
        "id": {
          "name": "id",
          "type": "integer",
          "primaryKey": true,
          "notNull": true,
          "autoincrement": true
        },
        "name": {
          "name": "name",
          "type": "text",
          "primaryKey": false,
          "notNull": true,
          "autoincrement": false
        },
        "description": {
          "name": "description",
          "type": "text",
          "primaryKey": false,
          "notNull": false,
          "autoincrement": false
        },
        "created_at": {
          "name": "created_at",
          "type": "integer",
          "primaryKey": false,
          "notNull": false,
          "autoincrement": false,
          "default": "'\"2025-09-03T16:07:20.494Z\"'"
        }
      },
      "indexes": {
        "categories_name_unique": {
          "name": "categories_name_unique",
          "columns": [
            "name"
          ],
          "isUnique": true
        }
      },
      "foreignKeys": {},
      "compositePrimaryKeys": {},
      "uniqueConstraints": {},
      "checkConstraints": {}
    },
    "devices_to_categories": {
      "name": "devices_to_categories",
      "columns": {
        "device_id": {
          "name": "device_id",
          "type": "integer",
          "primaryKey": false,
          "notNull": false,
          "autoincrement": false
        },
        "category_id": {
          "name": "category_id",
          "type": "integer",
          "primaryKey": false,
          "notNull": false,
          "autoincrement": false
        },
        "created_at": {
          "name": "created_at",
          "type": "integer",
          "primaryKey": false,
          "notNull": false,
          "autoincrement": false,
          "default": "'\"2025-09-03T16:07:20.495Z\"'"
        }
      },
      "indexes": {},
      "foreignKeys": {
        "devices_to_categories_device_id_devices_id_fk": {
          "name": "devices_to_categories_device_id_devices_id_fk",
          "tableFrom": "devices_to_categories",
          "tableTo": "devices",
          "columnsFrom": [
            "device_id"
          ],
          "columnsTo": [
            "id"
          ],
          "onDelete": "cascade",
          "onUpdate": "no action"
        },
        "devices_to_categories_category_id_categories_id_fk": {
          "name": "devices_to_categories_category_id_categories_id_fk",
          "tableFrom": "devices_to_categories",
          "tableTo": "categories",
          "columnsFrom": [
            "category_id"
          ],
          "columnsTo": [
            "id"
          ],
          "onDelete": "cascade",
          "onUpdate": "no action"
        }
      },
      "compositePrimaryKeys": {
        "devices_to_categories_device_id_category_id_pk": {
          "columns": [
            "device_id",
            "category_id"
          ],
          "name": "devices_to_categories_device_id_category_id_pk"
        }
      },
      "uniqueConstraints": {},
      "checkConstraints": {}
    },
    "devices": {
      "name": "devices",
      "columns": {
        "id": {
          "name": "id",
          "type": "integer",
          "primaryKey": true,
          "notNull": true,
          "autoincrement": true
        },
        "name": {
          "name": "name",
          "type": "text",
          "primaryKey": false,
          "notNull": true,
          "autoincrement": false
        },
        "brand": {
          "name": "brand",
          "type": "integer",
          "primaryKey": false,
          "notNull": false,
          "autoincrement": false
        },
        "model": {
          "name": "model",
          "type": "text",
          "primaryKey": false,
          "notNull": true,
          "autoincrement": false
        },
        "release_year": {
          "name": "release_year",
          "type": "integer",
          "primaryKey": false,
          "notNull": false,
          "autoincrement": false
        },
        "created_at": {
          "name": "created_at",
          "type": "integer",
          "primaryKey": false,
          "notNull": false,
          "autoincrement": false,
          "default": "'\"2025-09-03T16:07:20.495Z\"'"
        }
      },
      "indexes": {
        "devices_model_unique": {
          "name": "devices_model_unique",
          "columns": [
            "model"
          ],
          "isUnique": true
        }
      },
      "foreignKeys": {
        "devices_brand_brands_id_fk": {
          "name": "devices_brand_brands_id_fk",
          "tableFrom": "devices",
          "tableTo": "brands",
          "columnsFrom": [
            "brand"
          ],
          "columnsTo": [
            "id"
          ],
          "onDelete": "set null",
          "onUpdate": "no action"
        }
      },
      "compositePrimaryKeys": {},
      "uniqueConstraints": {},
      "checkConstraints": {}
    }
  },
  "views": {},
  "enums": {},
  "_meta": {
    "schemas": {},
    "tables": {},
    "columns": {}
  },
  "internal": {
    "indexes": {}
  }
}